pnmap/__init__.py
pnmap/arp.py
pnmap/console.py
pnmap/resolve.py
pnmap/scan.py
pnmap/subnet.py
pnmap-0.1.1.dist-info/entry_points.txt
pnmap-0.1.1.dist-info/LICENSE
pnmap-0.1.1.dist-info/WHEEL
pnmap-0.1.1.dist-info/METADATA
pnmap-0.1.1.dist-info/RECORD
